tessdata.py
tessdata-1.0.0.data/data/share/tessdata/osd.traineddata
tessdata-1.0.0.dist-info/LICENSE
tessdata-1.0.0.dist-info/LICENSE.tessdata
tessdata-1.0.0.dist-info/METADATA
tessdata-1.0.0.dist-info/WHEEL
tessdata-1.0.0.dist-info/top_level.txt
tessdata-1.0.0.dist-info/RECORD
