Metadata-Version: 2.1
Name: tessdata
Version: 1.0.0
Summary: contains tessdata osd and tessdata api
Home-page: https://github.com/asottile/tessdata
Author: Anthony Sottile
Author-email: asottile@umich.edu
License: MIT
Classifier: License :: OSI Approved :: MIT License
Classifier: Programming Language :: Python :: 3
Classifier: Programming Language :: Python :: 3 :: Only
Classifier: Programming Language :: Python :: Implementation :: CPython
Classifier: Programming Language :: Python :: Implementation :: PyPy
Requires-Python: >=3.8
License-File: LICENSE
License-File: LICENSE.tessdata
